odoo8_addon_website_legal_page-8.0.1.1.0.99.dev10-py3.8-nspkg.pth
odoo_addons/website_legal_page/README.rst
odoo_addons/website_legal_page/__init__.py
odoo_addons/website_legal_page/__openerp__.py
odoo_addons/website_legal_page/i18n/bg.po
odoo_addons/website_legal_page/i18n/ca.po
odoo_addons/website_legal_page/i18n/de.po
odoo_addons/website_legal_page/i18n/el_GR.po
odoo_addons/website_legal_page/i18n/es.po
odoo_addons/website_legal_page/i18n/fr.po
odoo_addons/website_legal_page/i18n/hr.po
odoo_addons/website_legal_page/i18n/hr_HR.po
odoo_addons/website_legal_page/i18n/it.po
odoo_addons/website_legal_page/i18n/pt_BR.po
odoo_addons/website_legal_page/i18n/pt_PT.po
odoo_addons/website_legal_page/i18n/ru.po
odoo_addons/website_legal_page/i18n/sl.po
odoo_addons/website_legal_page/i18n/website_legal_page.pot
odoo_addons/website_legal_page/static/description/icon.png
odoo_addons/website_legal_page/static/description/johnny-automatic-scales-of-justice.svg
odoo_addons/website_legal_page/views/reusable_templates.xml
odoo_addons/website_legal_page/views/website_legal.xml
odoo_addons/website_legal_page/views/website_privacy.xml
odoo_addons/website_legal_page/views/website_terms.xml
odoo8_addon_website_legal_page-8.0.1.1.0.99.dev10.dist-info/METADATA
odoo8_addon_website_legal_page-8.0.1.1.0.99.dev10.dist-info/WHEEL
odoo8_addon_website_legal_page-8.0.1.1.0.99.dev10.dist-info/namespace_packages.txt
odoo8_addon_website_legal_page-8.0.1.1.0.99.dev10.dist-info/top_level.txt
odoo8_addon_website_legal_page-8.0.1.1.0.99.dev10.dist-info/RECORD
